traceai_google_adk/__init__.py
traceai_google_adk/_wrappers.py
traceai_google_adk/version.py
traceai_google_adk-0.1.3.dist-info/METADATA
traceai_google_adk-0.1.3.dist-info/WHEEL
traceai_google_adk-0.1.3.dist-info/RECORD
