Metadata-Version: 2.3
Name: traceAI-google-adk
Version: 0.1.3
Summary: OpenTelemetry instrumentation for Google ADK
Author: Future AGI
Author-email: no-reply@futureagi.com
Requires-Python: >3.9,<3.13
Classifier: Programming Language :: Python :: 3
Classifier: Programming Language :: Python :: 3.10
Classifier: Programming Language :: Python :: 3.11
Classifier: Programming Language :: Python :: 3.12
Requires-Dist: fi-instrumentation-otel (>=0.1.14)
Requires-Dist: google-adk (>=1.2.1)
Requires-Dist: google-genai (>=1.0.0,<2.0.0)
